vitax/__init__.py
vitax/training.py
vitax/models/__init__.py
vitax/models/modeling.py
vitax/models/vit.py
vitax/models/vit_load_weights.py
vitax-0.0.4.dist-info/licenses/LICENSE
vitax-0.0.4.dist-info/METADATA
vitax-0.0.4.dist-info/WHEEL
vitax-0.0.4.dist-info/top_level.txt
vitax-0.0.4.dist-info/RECORD
