Metadata-Version: 2.4
Name: vitax
Version: 0.0.4
Summary: Vitax: Vision Transformers in Flax
Author-email: Mohammad Hassan Heydari <mheyddarii@gmail.com>
License: MIT License
Project-URL: Homepage, https://github.com/heydaari/vitax
Project-URL: Bug Tracker, https://github.com/heydaari/vitax/issues
Classifier: Programming Language :: Python :: 3
Classifier: License :: OSI Approved :: MIT License
Classifier: Operating System :: OS Independent
Requires-Python: >=3.10
License-File: LICENSE
Requires-Dist: jax
Requires-Dist: flax
Requires-Dist: optax
Dynamic: license-file
